odoo/addons/purchase_order_product_recommendation_forecast/README.rst
odoo/addons/purchase_order_product_recommendation_forecast/__init__.py
odoo/addons/purchase_order_product_recommendation_forecast/__manifest__.py
odoo/addons/purchase_order_product_recommendation_forecast/i18n/es.po
odoo/addons/purchase_order_product_recommendation_forecast/i18n/purchase_order_product_recommendation_forecast.pot
odoo/addons/purchase_order_product_recommendation_forecast/readme/CONTRIBUTORS.rst
odoo/addons/purchase_order_product_recommendation_forecast/readme/DESCRIPTION.rst
odoo/addons/purchase_order_product_recommendation_forecast/readme/USAGE.rst
odoo/addons/purchase_order_product_recommendation_forecast/static/description/icon.png
odoo/addons/purchase_order_product_recommendation_forecast/static/description/index.html
odoo/addons/purchase_order_product_recommendation_forecast/tests/__init__.py
odoo/addons/purchase_order_product_recommendation_forecast/tests/test_recommendation_forecast.py
odoo/addons/purchase_order_product_recommendation_forecast/wizards/__init__.py
odoo/addons/purchase_order_product_recommendation_forecast/wizards/purchase_order_recommendation.py
odoo/addons/purchase_order_product_recommendation_forecast/wizards/purchase_order_recommendation_view.xml
odoo12_addon_purchase_order_product_recommendation_forecast-12.0.1.0.0.99.dev4.dist-info/METADATA
odoo12_addon_purchase_order_product_recommendation_forecast-12.0.1.0.0.99.dev4.dist-info/WHEEL
odoo12_addon_purchase_order_product_recommendation_forecast-12.0.1.0.0.99.dev4.dist-info/top_level.txt
odoo12_addon_purchase_order_product_recommendation_forecast-12.0.1.0.0.99.dev4.dist-info/RECORD
